<annotation verified="yes">
	<folder>extract_images</folder>
	<filename>frame85.jpg</filename>
	<path>/home/amaad/Work/Classification/ANPR-Pakistan-Plate/extract_images/frame85.jpg</path>
	<source>
		<database>Unknown</database>
	</source>
	<size>
		<width>1920</width>
		<height>1080</height>
		<depth>3</depth>
	</size>
	<segmented>0</segmented>
	<object>
		<name>Undefined</name>
		<pose>Unspecified</pose>
		<truncated>0</truncated>
		<difficult>0</difficult>
		<bndbox>
			<xmin>769</xmin>
			<ymin>79</ymin>
			<xmax>887</xmax>
			<ymax>223</ymax>
		</bndbox>
	</object>
	<object>
		<name>Undefined</name>
		<pose>Unspecified</pose>
		<truncated>0</truncated>
		<difficult>0</difficult>
		<bndbox>
			<xmin>1073</xmin>
			<ymin>40</ymin>
			<xmax>1191</xmax>
			<ymax>86</ymax>
		</bndbox>
	</object>
	<object>
		<name>Undefined</name>
		<pose>Unspecified</pose>
		<truncated>0</truncated>
		<difficult>0</difficult>
		<bndbox>
			<xmin>752</xmin>
			<ymin>325</ymin>
			<xmax>939</xmax>
			<ymax>375</ymax>
		</bndbox>
	</object>
	<object>
		<name>Undefined</name>
		<pose>Unspecified</pose>
		<truncated>0</truncated>
		<difficult>0</difficult>
		<bndbox>
			<xmin>743</xmin>
			<ymin>518</ymin>
			<xmax>967</xmax>
			<ymax>638</ymax>
		</bndbox>
	</object>
	<object>
		<name>Undefined</name>
		<pose>Unspecified</pose>
		<truncated>0</truncated>
		<difficult>0</difficult>
		<bndbox>
			<xmin>960</xmin>
			<ymin>238</ymin>
			<xmax>1041</xmax>
			<ymax>303</ymax>
		</bndbox>
	</object>
	<object>
		<name>Number_Plate</name>
		<pose>Unspecified</pose>
		<truncated>0</truncated>
		<difficult>0</difficult>
		<bndbox>
			<xmin>715</xmin>
			<ymin>386</ymin>
			<xmax>976</xmax>
			<ymax>523</ymax>
		</bndbox>
	</object>
</annotation>
